orin3_grpc/__init__.py
orin3_grpc/design/__init__.py
orin3_grpc/design/orin3/__init__.py
orin3_grpc/design/orin3/common/__init__.py
orin3_grpc/design/orin3/common/v1/__init__.py
orin3_grpc/design/orin3/common/v1/orin3_common_pb2.py
orin3_grpc/design/orin3/common/v1/orin3_common_pb2_grpc.py
orin3_grpc/design/orin3/common/v1/orin3_common_remote_engine_pb2.py
orin3_grpc/design/orin3/common/v1/orin3_common_remote_engine_pb2_grpc.py
orin3_grpc/design/orin3/provider/__init__.py
orin3_grpc/design/orin3/provider/v1/__init__.py
orin3_grpc/design/orin3/provider/v1/orin3_object_type_pb2.py
orin3_grpc/design/orin3/provider/v1/orin3_object_type_pb2_grpc.py
orin3_grpc/design/orin3/provider/v1/orin3_value_type_pb2.py
orin3_grpc/design/orin3/provider/v1/orin3_value_type_pb2_grpc.py
orin3_grpc/message/__init__.py
orin3_grpc/message/orin3/__init__.py
orin3_grpc/message/orin3/provider/__init__.py
orin3_grpc/message/orin3/provider/v1/__init__.py
orin3_grpc/message/orin3/provider/v1/orin3_base_object_pb2.py
orin3_grpc/message/orin3/provider/v1/orin3_base_object_pb2_grpc.py
orin3_grpc/message/orin3/provider/v1/orin3_child_creator_pb2.py
orin3_grpc/message/orin3/provider/v1/orin3_child_creator_pb2_grpc.py
orin3_grpc/message/orin3/provider/v1/orin3_child_pb2.py
orin3_grpc/message/orin3/provider/v1/orin3_child_pb2_grpc.py
orin3_grpc/message/orin3/provider/v1/orin3_common_type_pb2.py
orin3_grpc/message/orin3/provider/v1/orin3_common_type_pb2_grpc.py
orin3_grpc/message/orin3/provider/v1/orin3_controller_creator_pb2.py
orin3_grpc/message/orin3/provider/v1/orin3_controller_creator_pb2_grpc.py
orin3_grpc/message/orin3/provider/v1/orin3_executable_pb2.py
orin3_grpc/message/orin3/provider/v1/orin3_executable_pb2_grpc.py
orin3_grpc/message/orin3/provider/v1/orin3_file_pb2.py
orin3_grpc/message/orin3/provider/v1/orin3_file_pb2_grpc.py
orin3_grpc/message/orin3/provider/v1/orin3_job_pb2.py
orin3_grpc/message/orin3/provider/v1/orin3_job_pb2_grpc.py
orin3_message_client-1.0.232.dist-info/licenses/LICENSE.txt
orin3_message_client-1.0.232.dist-info/METADATA
orin3_message_client-1.0.232.dist-info/WHEEL
orin3_message_client-1.0.232.dist-info/top_level.txt
orin3_message_client-1.0.232.dist-info/RECORD
