Metadata-Version: 2.4
Name: orin3-message-client
Version: 1.0.232
Summary: Package for a gRPC client connecting to ORiN3 Remote Engine / ORiN3 Provider.
Author: densowave
Author-email: contact.iot@denso-wave.com
Classifier: License :: Other/Proprietary License
Classifier: Programming Language :: Python :: 3
Classifier: Operating System :: OS Independent
Requires-Python: >=3.10
License-File: LICENSE.txt
Requires-Dist: grpcio~=1.68.0
Requires-Dist: grpcio-tools~=1.68.0
Dynamic: license-file
